telepot_mod/__init__.py
telepot_mod/api.py
telepot_mod/delegate.py
telepot_mod/exception.py
telepot_mod/filtering.py
telepot_mod/hack.py
telepot_mod/helper.py
telepot_mod/loop.py
telepot_mod/namedtuple.py
telepot_mod/routing.py
telepot_mod/text.py
telepot_mod/aio/__init__.py
telepot_mod/aio/api.py
telepot_mod/aio/delegate.py
telepot_mod/aio/hack.py
telepot_mod/aio/helper.py
telepot_mod/aio/loop.py
telepot_mod/aio/routing.py
telepot_mod-0.0.1.dist-info/METADATA
telepot_mod-0.0.1.dist-info/WHEEL
telepot_mod-0.0.1.dist-info/top_level.txt
telepot_mod-0.0.1.dist-info/RECORD
