Metadata-Version: 2.1
Name: telepot-mod
Version: 0.0.1
Summary: telepot_mod
Home-page: 
Author: telepot_mod
Author-email: telepot_mod@gmail.com
Classifier: Programming Language :: Python :: 3
Classifier: License :: OSI Approved :: GNU General Public License (GPL)
Classifier: Operating System :: OS Independent
Requires-Python: >=3.9
